{
  "stock_code": "139",
  "basic_information": {
    "公司名稱": "中國軟實力科技集團有限公司",
    "財政年度起始日": "2018/01/01",
    "財政年度截止日": "2018/12/31",
    "上市日期": "1994/03/15",
    "交易貨幣": "港元",
    "報告貨幣": "港元",
    "面值幣種": "港元",
    "股票面值": "0.01",
    "法定股本(股)": "80,000,000,000",
    "已發行股本(股)": "14,716,650,461",
    "已發行股本-H股(股)": "-",
    "買賣單位": "14,000",
    "每股淨資產值(港元)": "0.2142",
    "每股盈利(港元)": "0.0300",
    "市盈率(倍)": "1.97",
    "每股派息(港元)": "0.0000",
    "周息率(%)": "0.00",
    "股價/每股淨資產值(倍)": "0.2754",
    "指數成份股": "-"
  },
  "financial_ratio": {
    "截止日期": [
      "2013/03",
      "2014/03",
      "2015/03",
      "2016/03",
      "2017/03"
    ],
    "流動比率(倍)": [
      "9.89",
      "21.81",
      "5.39",
      "3.98",
      "12.18"
    ],
    "速動比率(倍)": [
      "9.86",
      "21.81",
      "5.39",
      "3.98",
      "12.18"
    ],
    "長期債項/股東權益(%)": [
      "580.25",
      "91.37",
      "0.03",
      "0.00",
      "6.58"
    ],
    "總債項/股東權益(%)": [
      "580.61",
      "91.46",
      "0.04",
      "0.00",
      "6.58"
    ],
    "總債項/資本運用(%)": [
      "102.13",
      "54.25",
      "0.05",
      "0.00",
      "6.17"
    ],
    "股東權益回報率(%)": [
      "-",
      "3.22",
      "-",
      "-",
      "-"
    ],
    "資本運用回報率(%)": [
      "-",
      "1.91",
      "-",
      "-",
      "-"
    ],
    "總資產回報率(%)": [
      "-",
      "1.83",
      "-",
      "-",
      "-"
    ],
    "經營利潤率(%)": [
      "-",
      "-",
      "-",
      "-",
      "-"
    ],
    "稅前利潤率(%)": [
      "-",
      "-",
      "-",
      "-",
      "-"
    ],
    "邊際利潤率(%)": [
      "-",
      "14.96",
      "-",
      "-",
      "-"
    ],
    "存貨周轉率(倍)": [
      "31.44",
      "0",
      "0",
      "0",
      "0"
    ],
    "派息比率(%)": [
      "0.00",
      "0.00",
      "0.00",
      "0.00",
      "0.00"
    ],
    "財政年度周最高價": [
      "0.369",
      "0.255",
      "12.300",
      "1.690",
      "0.305"
    ],
    "財政年度周最低價": [
      "0.156",
      "0.080",
      "0.215",
      "0.164",
      "0.145"
    ],
    "財政年度最高市盈率(倍)": [
      "-",
      "19.92",
      "-",
      "-",
      "-"
    ],
    "財政年度最低市盈率(倍)": [
      "-",
      "6.25",
      "-",
      "-",
      "-"
    ],
    "財政年度最高週息率(%)": [
      "0.00",
      "0.00",
      "0.00",
      "0.00",
      "0.00"
    ],
    "財政年度最低週息率(%)": [
      "0.00",
      "0.00",
      "0.00",
      "0.00",
      "0.00"
    ]
  },
  "profit_loss": {
    "截止日期": [
      "2014/03",
      "2015/03",
      "2016/03",
      "2017/03",
      "2017/12"
    ],
    "營業總額": [
      "36,119",
      "6,548",
      "-472,438",
      "-52,128",
      "228,055"
    ],
    "營業額": [
      "36,119",
      "6,548",
      "-472,438",
      "-52,128",
      "228,055"
    ],
    "營業額(其它)": [
      "-",
      "-",
      "-",
      "-",
      "-"
    ],
    "銷售成本": [
      "9,628",
      "11,075",
      "3,400",
      "3,257",
      "3,930"
    ],
    "毛利": [
      "26,491",
      "-4,527",
      "-475,838",
      "-55,385",
      "224,125"
    ],
    "除稅前溢利": [
      "-7,906",
      "-1,274,973",
      "-1,214,744",
      "-156,397",
      "373,375"
    ],
    "經營溢利": [
      "-7,906",
      "-1,277,056",
      "-1,128,958",
      "-171,963",
      "361,927"
    ],
    "特殊項目": [
      "-",
      "-",
      "-",
      "-",
      "-"
    ],
    "聯營公司": [
      "-",
      "-",
      "-",
      "-",
      "6,459"
    ],
    "非經營項目": [
      "0",
      "2,083",
      "-85,786",
      "15,566",
      "4,989"
    ],
    "稅項": [
      "-",
      "166",
      "1",
      "-",
      "4,520"
    ],
    "少數股東權益": [
      "-13,310",
      "-8,985",
      "37,892",
      "-",
      "-"
    ],
    "股東應佔溢利": [
      "5,404",
      "-1,266,154",
      "-1,252,637",
      "-156,397",
      "368,855"
    ],
    "單位": [
      "千",
      "千",
      "千",
      "千",
      "千"
    ],
    "貨幣": [
      "港元",
      "港元",
      "港元",
      "港元",
      "港元"
    ]
  },
  "balance_sheet": {
    "截止日期": [
      "2014/03",
      "2015/03",
      "2016/03",
      "2017/03",
      "2017/12"
    ],
    "非流動資產": [
      "16,183",
      "262,664",
      "662,754",
      "1,152,950",
      "2,156,116"
    ],
    "固定資產": [
      "1,722",
      "94,135",
      "3,216",
      "3,631",
      "435,006"
    ],
    "投資": [
      "14,461",
      "168,529",
      "655,121",
      "1,121,372",
      "1,710,695"
    ],
    "其他資產": [
      "-",
      "-",
      "4,417",
      "27,947",
      "10,415"
    ],
    "流動資產": [
      "279,530",
      "1,052,849",
      "362,790",
      "271,501",
      "2,072,532"
    ],
    "現金及銀行結存": [
      "83,769",
      "533,386",
      "86,467",
      "4,045",
      "123,387"
    ],
    "應收賬款": [
      "1,108",
      "1,442",
      "-",
      "-",
      "391,219"
    ],
    "存貨": [
      "-",
      "-",
      "-",
      "-",
      "-"
    ],
    "其他流動資產": [
      "194,653",
      "518,021",
      "276,323",
      "267,456",
      "1,557,926"
    ],
    "總資產": [
      "295,713",
      "1,315,513",
      "1,025,544",
      "1,424,451",
      "4,228,648"
    ],
    "非流動負債": [
      "154,209",
      "1,411",
      "-",
      "86,574",
      "250,764"
    ],
    "長期債項": [
      "153,319",
      "363",
      "-",
      "86,574",
      "250,630"
    ],
    "其他長期負債": [
      "890",
      "1,048",
      "-",
      "-",
      "134"
    ],
    "流動負債": [
      "12,815",
      "195,375",
      "91,088",
      "22,298",
      "1,253,980"
    ],
    "應付賬款": [
      "16",
      "3",
      "3",
      "502",
      "208,078"
    ],
    "稅項": [
      "12",
      "179",
      "179",
      "-",
      "9,023"
    ],
    "短期債項": [
      "142",
      "149",
      "-",
      "-",
      "753,187"
    ],
    "其他流動負債": [
      "12,645",
      "195,044",
      "90,906",
      "21,796",
      "283,692"
    ],
    "總負債": [
      "167,024",
      "196,786",
      "91,088",
      "108,872",
      "1,504,744"
    ],
    "股東權益": [
      "167,796",
      "1,164,955",
      "934,456",
      "1,315,579",
      "2,723,904"
    ],
    "股本": [
      "20,337",
      "41,908",
      "85,004",
      "89,651",
      "127,167"
    ],
    "儲備": [
      "147,459",
      "1,123,047",
      "849,452",
      "1,225,928",
      "2,596,737"
    ],
    "永久資本證券": [
      "-",
      "-",
      "-",
      "-",
      "-"
    ],
    "少數股東權益": [
      "-39,107",
      "-46,228",
      "-",
      "-",
      "-"
    ],
    "總權益": [
      "128,689",
      "1,118,727",
      "934,456",
      "1,315,579",
      "2,723,904"
    ],
    "單位": [
      "千",
      "千",
      "千",
      "千",
      "千"
    ],
    "貨幣": [
      "港元",
      "港元",
      "港元",
      "港元",
      "港元"
    ]
  },
  "cashflow": {
    "截止日期": [
      "2014/03",
      "2015/03",
      "2016/03",
      "2017/03",
      "2017/12"
    ],
    "經營活動之現金流量": [
      "-78,843",
      "-369,281",
      "-206,366",
      "-197,890",
      "-699,215"
    ],
    "投資回報及融資費用之現金流量": [
      "-27",
      "-3,671",
      "-160",
      "-22",
      "56,607"
    ],
    "已收利息": [
      "18",
      "16",
      "44",
      "9",
      "1"
    ],
    "已付利息": [
      "-45",
      "-3,687",
      "-204",
      "-31",
      "-43,764"
    ],
    "已收股息": [
      "-",
      "-",
      "-",
      "-",
      "100,370"
    ],
    "已付股息": [
      "-",
      "-",
      "-",
      "-",
      "-"
    ],
    "其他": [
      "-",
      "-",
      "31,013",
      "-",
      "-"
    ],
    "退回/(已繳)稅項": [
      "-",
      "-",
      "-",
      "-179",
      "-"
    ],
    "投資活動之現金流量": [
      "-27",
      "-244,442",
      "-1,171,480",
      "72,929",
      "-209,876"
    ],
    "增添固定資產": [
      "-27",
      "-1,207",
      "-3,229",
      "-18",
      "-990"
    ],
    "出售固定資產": [
      "-",
      "-",
      "6,580",
      "95",
      "-"
    ],
    "投資增加": [
      "-",
      "-260,000",
      "-1,359,359",
      "-197,653",
      "-291,209"
    ],
    "投資減少": [
      "-",
      "16,765",
      "184,528",
      "292,505",
      "82,323"
    ],
    "與關聯人士之現金流量": [
      "1,005",
      "1,868",
      "50,000",
      "-50,000",
      "122,000"
    ],
    "融資活動前之現金流量": [
      "-78,897",
      "-617,394",
      "-1,378,006",
      "-125,162",
      "-852,484"
    ],
    "融資活動之現金流量": [
      "131,371",
      "1,063,861",
      "934,887",
      "42,691",
      "912,358"
    ],
    "新增貸款": [
      "-",
      "-",
      "-",
      "-",
      "687,930"
    ],
    "償還貸款": [
      "-186",
      "-142",
      "-512",
      "-",
      "-96,056"
    ],
    "定息/債項工具融資": [
      "-",
      "-",
      "-",
      "92,100",
      "-"
    ],
    "償還定息/債項工具": [
      "-",
      "-",
      "-",
      "-",
      "-"
    ],
    "股本融資": [
      "130,552",
      "1,062,135",
      "854,386",
      "591",
      "198,484"
    ],
    "現金及等同現金之增加/(減少)": [
      "52,474",
      "446,467",
      "-443,119",
      "-82,471",
      "59,874"
    ],
    "年初之現金及現金等同項目": [
      "30,747",
      "83,223",
      "529,660",
      "86,516",
      "4,045"
    ],
    "外匯兌換率變動之影響/(其他)": [
      "2",
      "-30",
      "-25",
      "-",
      "-"
    ],
    "年終之現金及現金等同項目": [
      "83,223",
      "529,660",
      "86,516",
      "4,045",
      "63,919"
    ],
    "單位": [
      "千",
      "千",
      "千",
      "千",
      "千"
    ],
    "貨幣": [
      "港元",
      "港元",
      "港元",
      "港元",
      "港元"
    ],
    "核數師意見": [
      "無保留意見",
      "無保留意見",
      "無保留意見",
      "無保留意見",
      "無保留意見"
    ]
  },
  "dividend_history": [
    {
      "公佈日期": "2018/08/28",
      "年度/截至": "2018/12",
      "派息事項": "中期業績",
      "派息內容": "無派息",
      "方式": "-",
      "除淨日": "-",
      "截止過戶日期": "-",
      "派息日": "-"
    },
    {
      "公佈日期": "2018/03/23",
      "年度/截至": "2017/12",
      "派息事項": "末期業績",
      "派息內容": "無派息",
      "方式": "-",
      "除淨日": "-",
      "截止過戶日期": "-",
      "派息日": "-"
    },
    {
      "公佈日期": "2017/11/22",
      "年度/截至": "2017/12",
      "派息事項": "中期業績",
      "派息內容": "無派息",
      "方式": "-",
      "除淨日": "-",
      "截止過戶日期": "-",
      "派息日": "-"
    },
    {
      "公佈日期": "2017/06/23",
      "年度/截至": "2017/03",
      "派息事項": "末期業績",
      "派息內容": "無派息",
      "方式": "-",
      "除淨日": "-",
      "截止過戶日期": "-",
      "派息日": "-"
    },
    {
      "公佈日期": "2016/11/24",
      "年度/截至": "2017/03",
      "派息事項": "中期業績",
      "派息內容": "無派息",
      "方式": "-",
      "除淨日": "-",
      "截止過戶日期": "-",
      "派息日": "-"
    },
    {
      "公佈日期": "2016/06/22",
      "年度/截至": "2016/03",
      "派息事項": "末期業績",
      "派息內容": "無派息",
      "方式": "-",
      "除淨日": "-",
      "截止過戶日期": "-",
      "派息日": "-"
    },
    {
      "公佈日期": "2015/11/27",
      "年度/截至": "2016/03",
      "派息事項": "中期業績",
      "派息內容": "無派息",
      "方式": "-",
      "除淨日": "-",
      "截止過戶日期": "-",
      "派息日": "-"
    },
    {
      "公佈日期": "2015/06/26",
      "年度/截至": "2015/03",
      "派息事項": "末期業績",
      "派息內容": "無派息",
      "方式": "-",
      "除淨日": "-",
      "截止過戶日期": "-",
      "派息日": "-"
    },
    {
      "公佈日期": "2014/12/08",
      "年度/截至": "-",
      "派息事項": "特別報告",
      "派息內容": "合併: 10股合併為1股",
      "方式": "-",
      "除淨日": "2015/03/02",
      "截止過戶日期": "-",
      "派息日": "-"
    },
    {
      "公佈日期": "2014/12/08",
      "年度/截至": "-",
      "派息事項": "特別報告",
      "派息內容": "供股：1股合併後股份供6股@港元\n                0.1500",
      "方式": "-",
      "除淨日": "2015/03/03",
      "截止過戶日期": "2015/03/05-2015/03/10",
      "派息日": "2015/03/25"
    },
    {
      "公佈日期": "2014/12/08",
      "年度/截至": "-",
      "派息事項": "特別報告",
      "派息內容": "紅利股權證：每供6股送1份2016年認股權證",
      "方式": "實物",
      "除淨日": "2015/03/03",
      "截止過戶日期": "2015/03/05-2015/03/10",
      "派息日": "2015/04/08"
    },
    {
      "公佈日期": "2014/11/26",
      "年度/截至": "2015/03",
      "派息事項": "中期業績",
      "派息內容": "無派息",
      "方式": "-",
      "除淨日": "-",
      "截止過戶日期": "-",
      "派息日": "-"
    },
    {
      "公佈日期": "2014/06/19",
      "年度/截至": "2014/03",
      "派息事項": "末期業績",
      "派息內容": "無派息",
      "方式": "-",
      "除淨日": "-",
      "截止過戶日期": "-",
      "派息日": "-"
    },
    {
      "公佈日期": "2013/11/28",
      "年度/截至": "2014/03",
      "派息事項": "中期業績",
      "派息內容": "無派息",
      "方式": "-",
      "除淨日": "-",
      "截止過戶日期": "-",
      "派息日": "-"
    },
    {
      "公佈日期": "2013/06/26",
      "年度/截至": "-",
      "派息事項": "特別報告",
      "派息內容": "供股：1股供2股@港元 0.1000",
      "方式": "-",
      "除淨日": "2013/08/19",
      "截止過戶日期": "2013/08/21-2013/08/27",
      "派息日": "2013/09/11"
    },
    {
      "公佈日期": "2013/06/21",
      "年度/截至": "2013/03",
      "派息事項": "末期業績",
      "派息內容": "無派息",
      "方式": "-",
      "除淨日": "-",
      "截止過戶日期": "-",
      "派息日": "-"
    },
    {
      "公佈日期": "2013/02/04",
      "年度/截至": "2013/03",
      "派息事項": "特別報告",
      "派息內容": "合併: 5股合併為1股",
      "方式": "-",
      "除淨日": "2013/03/26",
      "截止過戶日期": "-",
      "派息日": "-"
    },
    {
      "公佈日期": "2012/11/28",
      "年度/截至": "2013/03",
      "派息事項": "中期業績",
      "派息內容": "無派息",
      "方式": "-",
      "除淨日": "-",
      "截止過戶日期": "-",
      "派息日": "-"
    },
    {
      "公佈日期": "2012/06/22",
      "年度/截至": "2012/03",
      "派息事項": "末期業績",
      "派息內容": "無派息",
      "方式": "-",
      "除淨日": "-",
      "截止過戶日期": "-",
      "派息日": "-"
    },
    {
      "公佈日期": "2011/11/22",
      "年度/截至": "2012/03",
      "派息事項": "中期業績",
      "派息內容": "無派息",
      "方式": "-",
      "除淨日": "-",
      "截止過戶日期": "-",
      "派息日": "-"
    },
    {
      "公佈日期": "2011/06/22",
      "年度/截至": "2011/03",
      "派息事項": "末期業績",
      "派息內容": "無派息",
      "方式": "-",
      "除淨日": "-",
      "截止過戶日期": "-",
      "派息日": "-"
    },
    {
      "公佈日期": "2010/11/24",
      "年度/截至": "2011/03",
      "派息事項": "中期業績",
      "派息內容": "無派息",
      "方式": "-",
      "除淨日": "-",
      "截止過戶日期": "-",
      "派息日": "-"
    },
    {
      "公佈日期": "2010/07/13",
      "年度/截至": "2010/03",
      "派息事項": "末期業績",
      "派息內容": "無派息",
      "方式": "-",
      "除淨日": "-",
      "截止過戶日期": "-",
      "派息日": "-"
    },
    {
      "公佈日期": "2009/12/01",
      "年度/截至": "2010/03",
      "派息事項": "中期業績",
      "派息內容": "無派息",
      "方式": "-",
      "除淨日": "-",
      "截止過戶日期": "-",
      "派息日": "-"
    },
    {
      "公佈日期": "2009/07/13",
      "年度/截至": "2009/03",
      "派息事項": "末期業績",
      "派息內容": "無派息",
      "方式": "-",
      "除淨日": "-",
      "截止過戶日期": "2009/08/21-2009/08/25",
      "派息日": "-"
    },
    {
      "公佈日期": "2008/12/08",
      "年度/截至": "2009/03",
      "派息事項": "中期業績",
      "派息內容": "無派息",
      "方式": "-",
      "除淨日": "-",
      "截止過戶日期": "-",
      "派息日": "-"
    },
    {
      "公佈日期": "2008/07/14",
      "年度/截至": "2008/03",
      "派息事項": "末期業績",
      "派息內容": "無派息",
      "方式": "-",
      "除淨日": "-",
      "截止過戶日期": "-",
      "派息日": "-"
    },
    {
      "公佈日期": "2007/12/07",
      "年度/截至": "2008/03",
      "派息事項": "中期業績",
      "派息內容": "無派息",
      "方式": "-",
      "除淨日": "-",
      "截止過戶日期": "-",
      "派息日": "-"
    },
    {
      "公佈日期": "2007/07/20",
      "年度/截至": "2007/03",
      "派息事項": "末期業績",
      "派息內容": "無派息",
      "方式": "-",
      "除淨日": "-",
      "截止過戶日期": "-",
      "派息日": "-"
    },
    {
      "公佈日期": "2006/12/14",
      "年度/截至": "2007/03",
      "派息事項": "中期業績",
      "派息內容": "無派息",
      "方式": "-",
      "除淨日": "-",
      "截止過戶日期": "-",
      "派息日": "-"
    },
    {
      "公佈日期": "2006/07/20",
      "年度/截至": "2006/03",
      "派息事項": "末期業績",
      "派息內容": "無派息",
      "方式": "-",
      "除淨日": "-",
      "截止過戶日期": "-",
      "派息日": "-"
    },
    {
      "公佈日期": "2005/06/21",
      "年度/截至": "2005/03",
      "派息事項": "特別報告",
      "派息內容": "合併: 10股合併為1股",
      "方式": "-",
      "除淨日": "2005/07/29",
      "截止過戶日期": "-",
      "派息日": "-"
    }
  ],
  "earning_summary": {
    "截止日期": [
      "2014/03",
      "2015/03",
      "2016/03",
      "2017/03",
      "2017/12"
    ],
    "盈利(百萬)": [
      "5",
      "-1,266",
      "-1,253",
      "-156",
      "369"
    ],
    "盈利增長(%)": [
      "-187.18",
      "-23529.94",
      "-1.07",
      "-87.51",
      "-"
    ],
    "每股盈利": [
      "0.0128",
      "-1.1000",
      "-0.1800",
      "-0.0200",
      "0.0300"
    ],
    "每股盈利增長(%)": [
      "-280.28",
      "-8693.75",
      "-83.64",
      "-88.89",
      "-"
    ],
    "每股派息": [
      "0.0000",
      "0.0000",
      "0.0000",
      "0.0000",
      "0.0000"
    ],
    "市盈率(倍)": [
      "68.75",
      "-0.25",
      "-1.08",
      "-6.35",
      "1.97"
    ],
    "周息率(%)": [
      "0.00",
      "0.00",
      "0.00",
      "0.00",
      "0.00"
    ],
    "派息比率(%)": [
      "0.00",
      "0.00",
      "0.00",
      "0.00",
      "0.00"
    ],
    "每股賬面資產淨值": [
      "0.0825",
      "0.2780",
      "0.1099",
      "0.1467",
      "0.2142"
    ],
    "基準貨幣": [
      "港元",
      "港元",
      "港元",
      "港元",
      "港元"
    ],
    "兌換比率": [
      "1",
      "1",
      "1",
      "1",
      "1"
    ]
  }
}
