{
  "stock_code": "1986",
  "basic_information": {
    "Name": "Tsaker Chemical Group Ltd.",
    "EPS Start Date": "2018/01/01",
    "EPS End Date": "2018/12/31",
    "Listing Date": "2015/07/03",
    "Trade Currency": "HKD",
    "Report Currency": "RMB",
    "Par Currency": "USD",
    "Par": "0.01",
    "Authorized Capital(share)": "2,000,000,000",
    "Issued Capital(share)": "1,044,250,000",
    "Issue Cap-H(share)": "-",
    "Board Lot": "500",
    "NAV(HKD)": "1.3103",
    "EPS(HKD)": "0.1559",
    "PE": "0.00",
    "DPS(HKD)": "0.0468",
    "Yield": "-",
    "Price/PNAV": "-",
    "Index Constituent": "-"
  },
  "financial_ratio": {
    "Closing Date": [
      "2013/12",
      "2014/12",
      "2015/12",
      "2016/12",
      "2017/12"
    ],
    "Current Ratio (X)": [
      "1.22",
      "0.89",
      "1.42",
      "1.29",
      "1.39"
    ],
    "Quick Ratio (X)": [
      "0.99",
      "0.72",
      "1.29",
      "1.18",
      "1.22"
    ],
    "Long Term Debt/Equity (%)": [
      "7.25",
      "0.00",
      "0.00",
      "24.97",
      "33.95"
    ],
    "Total Debt/Equity (%)": [
      "48.33",
      "26.40",
      "37.68",
      "50.12",
      "50.99"
    ],
    "Total Debt/Capital Employed (%)": [
      "37.60",
      "23.50",
      "37.31",
      "39.39",
      "37.53"
    ],
    "Return on Equity (%)": [
      "39.70",
      "47.21",
      "12.14",
      "12.58",
      "11.93"
    ],
    "Return on Capital Employ (%)": [
      "30.88",
      "42.03",
      "12.02",
      "9.89",
      "8.78"
    ],
    "Return on Total Assets (%)": [
      "14.58",
      "20.56",
      "7.02",
      "6.23",
      "6.03"
    ],
    "Operating Profit Margin (%)": [
      "20.18",
      "25.21",
      "17.35",
      "14.84",
      "14.52"
    ],
    "Pre-tax Profit Margin (%)": [
      "20.18",
      "25.21",
      "16.87",
      "14.84",
      "14.52"
    ],
    "Net Profit Margin (%)": [
      "12.67",
      "16.14",
      "11.68",
      "11.61",
      "10.91"
    ],
    "Inventory Turnover (X)": [
      "9.66",
      "14.86",
      "11.25",
      "12.73",
      "10.85"
    ],
    "Dividend Payout (%)": [
      "0.00",
      "0.00",
      "26.96",
      "60.83",
      "30.00"
    ],
    "Fiscal Year High": [
      "0",
      "0",
      "0",
      "0",
      "0"
    ],
    "Fiscal Year Low": [
      "0",
      "0",
      "0",
      "0",
      "0"
    ],
    "Fiscal Year PER Range High (X)": [
      "-",
      "-",
      "-",
      "-",
      "-"
    ],
    "Fiscal Year PER Range Low (X)": [
      "-",
      "-",
      "-",
      "-",
      "-"
    ],
    "Fiscal Year Yield Range High (%)": [
      "0.00",
      "0.00",
      "0.00",
      "0.00",
      "0.00"
    ],
    "Fiscal Year Yield Range Low (%)": [
      "0.00",
      "0.00",
      "0.00",
      "0.00",
      "0.00"
    ]
  },
  "profit_loss": {
    "Closing Date": [
      "2013/12",
      "2014/12",
      "2015/12",
      "2016/12",
      "2017/12"
    ],
    "Total Turnover": [
      "863,969",
      "897,477",
      "880,270",
      "1,041,142",
      "1,247,392"
    ],
    "Turnover": [
      "863,969",
      "897,477",
      "880,270",
      "1,041,142",
      "1,247,392"
    ],
    "Other Turnover": [
      "-",
      "-",
      "-",
      "-",
      "-"
    ],
    "Cost of Sales": [
      "606,936",
      "555,242",
      "612,939",
      "747,537",
      "884,403"
    ],
    "Gross Profit": [
      "257,033",
      "342,235",
      "267,331",
      "293,605",
      "362,989"
    ],
    "Profit Before Taxation": [
      "174,331",
      "226,234",
      "141,353",
      "154,458",
      "181,059"
    ],
    "Operating Profit": [
      "174,331",
      "226,234",
      "141,353",
      "154,458",
      "181,059"
    ],
    "Exceptional Items": [
      "-",
      "-",
      "-",
      "-",
      "-"
    ],
    "Associates": [
      "-",
      "-",
      "-",
      "-",
      "-"
    ],
    "Other Non-Operating Gains": [
      "0",
      "0",
      "0",
      "0",
      "0"
    ],
    "Taxation": [
      "41,343",
      "54,720",
      "43,883",
      "33,537",
      "44,953"
    ],
    "Minority Interests": [
      "23,548",
      "26,655",
      "-",
      "-",
      "-25"
    ],
    "Net Profit": [
      "109,440",
      "144,859",
      "97,470",
      "120,921",
      "136,131"
    ],
    "Unit": [
      "Thousand",
      "Thousand",
      "Thousand",
      "Thousand",
      "Thousand"
    ],
    "Currency": [
      "RMB",
      "RMB",
      "RMB",
      "RMB",
      "RMB"
    ]
  },
  "balance_sheet": {
    "Closing Date": [
      "2013/12",
      "2014/12",
      "2015/12",
      "2016/12",
      "2017/12"
    ],
    "Non Current Assets": [
      "267,029",
      "383,346",
      "849,555",
      "1,013,486",
      "1,278,371"
    ],
    "Fixed Assets": [
      "251,665",
      "323,743",
      "733,012",
      "882,002",
      "1,119,738"
    ],
    "Investments": [
      "-",
      "-",
      "-",
      "19,200",
      "32,151"
    ],
    "Other Assets": [
      "15,364",
      "59,603",
      "116,543",
      "112,284",
      "126,482"
    ],
    "Current Assets": [
      "483,577",
      "321,142",
      "891,027",
      "926,247",
      "977,883"
    ],
    "Cash On Hand": [
      "21,625",
      "95,471",
      "494,708",
      "469,204",
      "377,655"
    ],
    "Receivables": [
      "167,342",
      "147,663",
      "235,579",
      "281,029",
      "328,238"
    ],
    "Inventory": [
      "89,434",
      "60,383",
      "79,169",
      "81,765",
      "114,967"
    ],
    "Other Current Assets": [
      "205,176",
      "17,625",
      "81,571",
      "94,249",
      "157,023"
    ],
    "Total Assets": [
      "750,606",
      "704,488",
      "1,740,582",
      "1,939,733",
      "2,256,254"
    ],
    "Non Current Liabilities": [
      "28,931",
      "37,836",
      "8,356",
      "261,801",
      "408,976"
    ],
    "Long Term Debt": [
      "20,000",
      "-",
      "-",
      "240,000",
      "387,421"
    ],
    "Other Long Term Liabilities": [
      "8,931",
      "37,836",
      "8,356",
      "21,801",
      "21,555"
    ],
    "Current Liabilities": [
      "396,187",
      "359,806",
      "869,674",
      "716,947",
      "705,342"
    ],
    "Payables": [
      "129,892",
      "149,144",
      "250,447",
      "256,523",
      "369,798"
    ],
    "Taxation": [
      "847",
      "22,406",
      "-",
      "19,634",
      "15,000"
    ],
    "Short Term Debt": [
      "113,246",
      "81,000",
      "317,320",
      "241,622",
      "194,576"
    ],
    "Other Current Liabilities": [
      "152,202",
      "107,256",
      "301,907",
      "199,168",
      "125,968"
    ],
    "Total Liabilities": [
      "425,118",
      "397,642",
      "878,030",
      "978,748",
      "1,114,318"
    ],
    "Owner's Equity": [
      "275,688",
      "306,846",
      "862,552",
      "960,985",
      "1,141,291"
    ],
    "Share Capital": [
      "-",
      "6",
      "30,649",
      "30,649",
      "67,491"
    ],
    "Reserves": [
      "275,688",
      "306,840",
      "831,903",
      "930,336",
      "1,073,800"
    ],
    "Perpetual Capital Securities": [
      "-",
      "-",
      "-",
      "-",
      "-"
    ],
    "Minority interests": [
      "49,800",
      "-",
      "-",
      "-",
      "645"
    ],
    "Total Equity": [
      "325,488",
      "306,846",
      "862,552",
      "960,985",
      "1,141,936"
    ],
    "Unit": [
      "Thousand",
      "Thousand",
      "Thousand",
      "Thousand",
      "Thousand"
    ],
    "Currency": [
      "RMB",
      "RMB",
      "RMB",
      "RMB",
      "RMB"
    ]
  },
  "cashflow": {
    "Closing Date": [
      "2013/12",
      "2014/12",
      "2015/12",
      "2016/12",
      "2017/12"
    ],
    "Net Cash Flow from Operating Activities": [
      "178,283",
      "342,924",
      "124,581",
      "170,498",
      "253,154"
    ],
    "Net Cash Flow from Return on Investments & Servicing of Finance": [
      "-19,575",
      "-39,917",
      "-4,832",
      "-29,207",
      "-52,397"
    ],
    "Interest Received": [
      "332",
      "277",
      "2,547",
      "12,180",
      "1,277"
    ],
    "Interest Paid": [
      "-19,907",
      "-9,226",
      "-7,379",
      "-10,317",
      "-15,559"
    ],
    "Dividend Received": [
      "-",
      "-",
      "-",
      "-",
      "-"
    ],
    "Dividend Paid": [
      "-",
      "-30,968",
      "-",
      "-31,070",
      "-38,115"
    ],
    "Others": [
      "-173,590",
      "30,615",
      "-300,000",
      "228,617",
      "-5,000"
    ],
    "Taxes (Paid) / Refunded": [
      "-6,200",
      "-46,631",
      "-80,444",
      "-1,051",
      "-47,307"
    ],
    "Net Cash Flow from Investing Activities": [
      "-46,880",
      "-120,759",
      "-214,035",
      "-248,092",
      "-257,268"
    ],
    "Additions to Fixed Assets": [
      "-57,877",
      "-111,419",
      "-184,505",
      "-229,577",
      "-245,968"
    ],
    "Disposal of Fixed Assets": [
      "398",
      "645",
      "2,317",
      "1,323",
      "227"
    ],
    "Increase in Investments": [
      "-",
      "-",
      "-",
      "-35,661",
      "-12,951"
    ],
    "Decrease in Investments": [
      "-",
      "-",
      "-",
      "-",
      "-"
    ],
    "Net Cash Flow with Related Parties": [
      "14,934",
      "-182,894",
      "-48,471",
      "-91,583",
      "-87,263"
    ],
    "Net Cash Flow before Financing Activities": [
      "105,628",
      "135,617",
      "-174,730",
      "-107,852",
      "-103,818"
    ],
    "Net Cash Flow from Financing Activities": [
      "-131,087",
      "-61,403",
      "266,690",
      "301,336",
      "65,701"
    ],
    "New Loans": [
      "279,199",
      "171,000",
      "412,320",
      "499,942",
      "567,115"
    ],
    "Loans Repayment": [
      "-251,630",
      "-214,831",
      "-176,000",
      "-335,640",
      "-503,097"
    ],
    "Fixed Income/Debt Instruments": [
      "-",
      "-",
      "-",
      "-",
      "-"
    ],
    "Repayment of Fixed Income/Debt Instruments": [
      "-",
      "-",
      "-",
      "-",
      "-"
    ],
    "Equity Financing": [
      "-",
      "134,707",
      "378,841",
      "-",
      "93,946"
    ],
    "Increase(Decrease) in Cash & Cash Equivalents": [
      "-25,459",
      "74,214",
      "91,960",
      "193,484",
      "-38,117"
    ],
    "Cash & Cash Equivalents at Beginning of Year": [
      "46,701",
      "21,113",
      "95,471",
      "194,192",
      "396,743"
    ],
    "Net Cash Flow due to Change in Exchange Rate/Others": [
      "-129",
      "144",
      "5,442",
      "9,067",
      "1,161"
    ],
    "Cash & Cash Equivalents at End of Year": [
      "21,113",
      "95,471",
      "192,873",
      "396,743",
      "359,787"
    ],
    "Unit": [
      "Thousand",
      "Thousand",
      "Thousand",
      "Thousand",
      "Thousand"
    ],
    "Currency": [
      "RMB",
      "RMB",
      "RMB",
      "RMB",
      "RMB"
    ],
    "Auditor's Opinion": [
      "-",
      "-",
      "Unqualified",
      "Unqualified",
      "Unqualified"
    ]
  },
  "dividend_history": [
    {
      "Announce Date": "2018/08/24",
      "Year Ended": "2018/12",
      "Event": "Interim",
      "Particular": "No Dividend",
      "Type": "-",
      "Ex-Date": "-",
      "Book Close Date": "-",
      "Payable Date": "-"
    },
    {
      "Announce Date": "2018/03/28",
      "Year Ended": "2017/12",
      "Event": "Final",
      "Particular": "D:RMB\n                0.0390(equivalent to HKD 0.0480)",
      "Type": "Cash",
      "Ex-Date": "2018/06/22",
      "Book Close Date": "2018/06/26-2018/06/29",
      "Payable Date": "2018/07/13"
    },
    {
      "Announce Date": "2017/08/23",
      "Year Ended": "2017/12",
      "Event": "Interim",
      "Particular": "No Dividend",
      "Type": "-",
      "Ex-Date": "-",
      "Book Close Date": "-",
      "Payable Date": "-"
    },
    {
      "Announce Date": "2017/03/29",
      "Year Ended": "2016/12",
      "Event": "Final",
      "Particular": "D:RMB\n                0.0730(equivalent to HKD 0.0840)",
      "Type": "Cash",
      "Ex-Date": "2017/06/23",
      "Book Close Date": "2017/06/27-2017/06/30",
      "Payable Date": "2017/07/13"
    },
    {
      "Announce Date": "2017/03/29",
      "Year Ended": "2016/12",
      "Event": "Final",
      "Particular": "B:1-for-1",
      "Type": "Scrip",
      "Ex-Date": "2017/06/23",
      "Book Close Date": "2017/06/27-2017/06/30",
      "Payable Date": "2017/07/13"
    },
    {
      "Announce Date": "2016/08/25",
      "Year Ended": "2016/12",
      "Event": "Interim",
      "Particular": "No Dividend",
      "Type": "-",
      "Ex-Date": "-",
      "Book Close Date": "-",
      "Payable Date": "-"
    },
    {
      "Announce Date": "2016/03/29",
      "Year Ended": "2015/12",
      "Event": "Final",
      "Particular": "D:RMB\n                0.0620(equivalent to HKD 0.0730)",
      "Type": "Cash",
      "Ex-Date": "2016/06/21",
      "Book Close Date": "2016/06/23-2016/06/27",
      "Payable Date": "2016/07/08"
    },
    {
      "Announce Date": "2015/08/25",
      "Year Ended": "2015/12",
      "Event": "Interim",
      "Particular": "No Dividend",
      "Type": "-",
      "Ex-Date": "-",
      "Book Close Date": "-",
      "Payable Date": "-"
    }
  ],
  "earning_summary": {
    "Closing Date": [
      "2013/12",
      "2014/12",
      "2015/12",
      "2016/12",
      "2017/12"
    ],
    "Net Profit (Mn)": [
      "140",
      "181",
      "115",
      "134",
      "163"
    ],
    "Net Profit Growth (%)": [
      "8.67",
      "29.04",
      "-36.59",
      "17.22",
      "21.46"
    ],
    "Earnings Per Share": [
      "0.0000",
      "0.0000",
      "0.2587",
      "0.1334",
      "0.1559"
    ],
    "EPS Growth (%)": [
      "-",
      "-",
      "-",
      "-48.46",
      "-41.56"
    ],
    "Dividend Per Share": [
      "0.0000",
      "0.0000",
      "0.0729",
      "0.0811",
      "0.0468"
    ],
    "PE (X)": [
      "-",
      "-",
      "0.00",
      "0.00",
      "0.00"
    ],
    "Yield (%)": [
      "-",
      "-",
      "-",
      "-",
      "-"
    ],
    "Dividend Payout (%)": [
      "-",
      "-",
      "28.18",
      "60.83",
      "30.00"
    ],
    "NAV": [
      "0.0000",
      "0.0000",
      "2.0243",
      "2.1310",
      "1.3103"
    ],
    "Currency": [
      "HKD",
      "HKD",
      "HKD",
      "HKD",
      "HKD"
    ],
    "Currency Conversion": [
      "1.28",
      "1.2479",
      "1.1761",
      "1.11125",
      "1.1989"
    ]
  }
}
